Metadata-Version: 2.1
Name: odoo12-addon-mis-builder-operating-unit
Version: 12.0.1.0.0.99.dev9
Summary: MIS Builder with Operating Unit
Home-page: https://github.com/operating-unit
Author: Eficent Business and IT Consulting Services S.L., Serpent Consulting Services Pvt. Ltd.,ACSONE SA/NV,Odoo Community Association (OCA)
Author-email: support@odoo-community.org
License: LGPL-3
Platform: UNKNOWN
Classifier: Programming Language :: Python
Classifier: Framework :: Odoo
Classifier: Framework :: Odoo :: 12.0
Classifier: License :: OSI Approved :: GNU Lesser General Public License v3 (LGPLv3)
Requires-Python: >=3.5
Requires-Dist: odoo12-addon-account-operating-unit
Requires-Dist: odoo12-addon-mis-builder
Requires-Dist: odoo <12.1dev,>=12.0a
